deploy_ciscoasa_cert/__init__.py
deploy_ciscoasa_cert/cisco_asa.py
deploy_ciscoasa_cert/main.py
deploy_ciscoasa_cert-0.1.1.dist-info/entry_points.txt
deploy_ciscoasa_cert-0.1.1.dist-info/WHEEL
deploy_ciscoasa_cert-0.1.1.dist-info/METADATA
deploy_ciscoasa_cert-0.1.1.dist-info/RECORD
